dgraph_flex/__init__.py
dgraph_flex/dgraph_flex.py
dgraph_flex/modify_graph.py
dgraph_flex-0.1.11.dist-info/licenses/LICENSE
dgraph_flex-0.1.11.dist-info/METADATA
dgraph_flex-0.1.11.dist-info/WHEEL
dgraph_flex-0.1.11.dist-info/top_level.txt
dgraph_flex-0.1.11.dist-info/RECORD
