Metadata-Version: 2.4
Name: dgraph_flex
Version: 0.1.11
Summary: A package for working with directed graphs
Author-email: "Kelvin O. Lim" <lim.kelvino@gmail.com>
Project-URL: Homepage, https://github.com/kelvinlim/dgraph_flex
Project-URL: Bug Tracker, https://github.com/kelvinlim/dgraph_flex/issues
Classifier: Programming Language :: Python :: 3
Classifier: License :: OSI Approved :: MIT License
Classifier: Operating System :: OS Independent
Requires-Python: >=3.10
License-File: LICENSE
Requires-Dist: graphviz
Requires-Dist: pyaml
Requires-Dist: matplotlib
Dynamic: license-file
